text2sqlMetadataFilterer/__init__.py
text2sqlMetadataFilterer/local.py
text2sqlMetadataFilterer/remote.py
text2sqlMetadataFilterer/utils.py
text2sqlMetadataFilterer/ZhipuAI/ZhipuAI_Chat.py
text2sqlMetadataFilterer/ZhipuAI/ZhipuAI_embeddings.py
text2sqlMetadataFilterer/ZhipuAI/__init__.py
text2sqlMetadataFilterer/advanced/__init__.py
text2sqlMetadataFilterer/anthropic/__init__.py
text2sqlMetadataFilterer/anthropic/anthropic_chat.py
text2sqlMetadataFilterer/base/__init__.py
text2sqlMetadataFilterer/base/base.py
text2sqlMetadataFilterer/bedrock/__init__.py
text2sqlMetadataFilterer/bedrock/bedrock_converse.py
text2sqlMetadataFilterer/chromadb/__init__.py
text2sqlMetadataFilterer/chromadb/chromadb_vector.py
text2sqlMetadataFilterer/exceptions/__init__.py
text2sqlMetadataFilterer/flask/__init__.py
text2sqlMetadataFilterer/flask/assets.py
text2sqlMetadataFilterer/flask/auth.py
text2sqlMetadataFilterer/google/__init__.py
text2sqlMetadataFilterer/google/gemini_chat.py
text2sqlMetadataFilterer/hf/__init__.py
text2sqlMetadataFilterer/hf/hf.py
text2sqlMetadataFilterer/marqo/__init__.py
text2sqlMetadataFilterer/marqo/marqo.py
text2sqlMetadataFilterer/milvus/__init__.py
text2sqlMetadataFilterer/milvus/milvus_vector.py
text2sqlMetadataFilterer/mistral/__init__.py
text2sqlMetadataFilterer/mistral/mistral.py
text2sqlMetadataFilterer/mock/__init__.py
text2sqlMetadataFilterer/mock/embedding.py
text2sqlMetadataFilterer/mock/llm.py
text2sqlMetadataFilterer/mock/vectordb.py
text2sqlMetadataFilterer/ollama/__init__.py
text2sqlMetadataFilterer/ollama/ollama.py
text2sqlMetadataFilterer/openai/__init__.py
text2sqlMetadataFilterer/openai/openai_chat.py
text2sqlMetadataFilterer/openai/openai_embeddings.py
text2sqlMetadataFilterer/opensearch/__init__.py
text2sqlMetadataFilterer/opensearch/opensearch_vector.py
text2sqlMetadataFilterer/pinecone/__init__.py
text2sqlMetadataFilterer/pinecone/pinecone_vector.py
text2sqlMetadataFilterer/qdrant/__init__.py
text2sqlMetadataFilterer/qdrant/qdrant.py
text2sql_metadata_filterer-0.1.1.dist-info/LICENSE
text2sql_metadata_filterer-0.1.1.dist-info/METADATA
text2sql_metadata_filterer-0.1.1.dist-info/WHEEL
text2sql_metadata_filterer-0.1.1.dist-info/top_level.txt
text2sql_metadata_filterer-0.1.1.dist-info/RECORD
